daas_service_sdk/__init__.py
daas_service_sdk/base_client.py
daas_service_sdk/service_base_client.py
daas_service_sdk/credentials/__init__.py
daas_service_sdk/credentials/base_credential.py
daas_service_sdk/credentials/basic_credential.py
daas_service_sdk/credentials/simple_credential.py
daas_service_sdk/entitlements/__init__.py
daas_service_sdk/entitlements/_client.py
daas_service_sdk-0.0.6.dist-info/LICENSE
daas_service_sdk-0.0.6.dist-info/METADATA
daas_service_sdk-0.0.6.dist-info/WHEEL
daas_service_sdk-0.0.6.dist-info/top_level.txt
daas_service_sdk-0.0.6.dist-info/RECORD
