Metadata-Version: 2.1
Name: daas-service-sdk
Version: 0.0.6
Summary: Daas Service SDK for Python
Home-page: https://github.com/grasp-labs/daas-service-sdk-python
Author: Grasp Labs
Author-email: yuan@grasplabs.com
License: MIT
Project-URL: Issue Tracker, https://github.com/grasp-labs/daas-service-sdk-python/issues
Keywords: daas service sdk python
Classifier: Development Status :: 3 - Alpha
Classifier: Intended Audience :: Developers
Classifier: Topic :: Software Development :: Build Tools
Classifier: Environment :: Console
Classifier: License :: OSI Approved :: MIT License
Classifier: Natural Language :: English
Classifier: Programming Language :: Python :: 3.7
Classifier: Programming Language :: Python :: 3.8
Classifier: Programming Language :: Python :: 3.9
Classifier: Programming Language :: Python :: 3.10
Requires-Python: >=3.7
License-File: LICENSE
Requires-Dist: requests
